{
	"id": "a73c6380-62e8-4900-b02a-f471d2eefbe1",
	"name": "SD-WAN Environment",
	"values": [
		{
			"key": "username",
			"value": "username",
			"enabled": true
		},
		{
			"key": "password",
			"value": "password",
			"enabled": true
		},
		{
			"key": "site_id",
			"value": "The Site ID",
			"type": "default",
			"enabled": true
		},
		{
			"key": "routing_id",
			"value": "Routing Setting ID",
			"type": "default",
			"enabled": true
		},
		{
			"key": "network_policy_id",
			"value": "The Network Policy ID",
			"type": "default",
			"enabled": true
		},
		{
			"key": "vpn_zone_id",
			"value": "VPN Zone ID",
			"type": "default",
			"enabled": true
		},
		{
			"key": "vpn_policy_id",
			"value": "VPN Policy ID",
			"type": "default",
			"enabled": true
		},
		{
			"key": "internet_access_policy_id",
			"value": "The Internet Access Policy ID",
			"type": "default",
			"enabled": true
		},
		{
			"key": "swg_id",
			"value": "The Secure Web Gateway ID",
			"type": "default",
			"enabled": true
		},
		{
			"key": "appliance_template_id",
			"value": "The Appliance Template ID",
			"type": "default",
			"enabled": true
		},
		{
			"key": "lan_id",
			"value": "The LAN ID",
			"type": "default",
			"enabled": true
		},
		{
			"key": "wan_id",
			"value": "The WAN Configuration ID",
			"type": "default",
			"enabled": true
		},
		{
			"key": "application_group_id",
			"value": "Application groups ID",
			"type": "default",
			"enabled": true
		},
		{
			"key": "overlay_id",
			"value": "The Overlay ID",
			"type": "default",
			"enabled": true
		},
		{
			"key": "transport_networks_id",
			"value": "Transport networks ID",
			"type": "default",
			"enabled": true
		},
		{
			"key": "user_subnet_id",
			"value": "User subnets ID",
			"type": "default",
			"enabled": true
		},
		{
			"key": "application_id",
			"value": "applications ID",
			"type": "default",
			"enabled": true
		},
		{
			"key": "saas_applications_id",
			"value": "SaaS Applications ID",
			"type": "default",
			"enabled": true
		},
		{
			"key": "dws_policies_id",
			"value": "DWS Policies ID",
			"type": "default",
			"enabled": true
		},
		{
			"key": "qos_profiles_id",
			"value": "QoS Profiles ID",
			"type": "default",
			"enabled": true
		},
		{
			"key": "ihap_profiles_id",
			"value": "IHAP Profiles ID",
			"type": "default",
			"enabled": true
		},
		{
			"key": "vrrp_profiles_id",
			"value": "VRRP Profiles ID",
			"type": "default",
			"enabled": true
		},
		{
			"key": "appliance_id",
			"value": "Appliance ID",
			"type": "default",
			"enabled": true
		},
		{
			"key": "serialNumber",
			"value": "Appliance serial number",
			"type": "default",
			"enabled": true
		},
		{
			"key": "deployment_snapshot_id",
			"value": "Validated Deployment snapshot ID",
			"type": "default",
			"enabled": true
		},
		{
			"key": "wan_interface",
			"value": "Name of the WAN Interface\n\nExample : wan1",
			"type": "default",
			"enabled": true
		},
		{
			"key": "connection_type",
			"value": "Connections Types\n\nExample : site-to-site, hub-and-spoke, third-party-vpn, secure-web-gateway, apps-anywhere",
			"type": "default",
			"enabled": true
		},
		{
			"key": "vlan_id",
			"value": "VLAN ID",
			"type": "default",
			"enabled": true
		},
		{
			"key": "dhcp_service_id",
			"value": "DHCP Service ID",
			"type": "default",
			"enabled": true
		},
		{
			"key": "protocol_id",
			"value": "Protocol ID",
			"type": "default",
			"enabled": true
		},
		{
			"key": "troubleshooting_request_id",
			"value": "Troubleshooting Session ID",
			"type": "default",
			"enabled": true
		},
		{
			"key": "count",
			"value": "1",
			"type": "default",
			"enabled": true
		},
		{
			"key": "jwttoken",
			"value": "",
			"type": "any",
			"enabled": true
		},
		{
			"key": "myEpoch",
			"value": "",
			"type": "any",
			"enabled": true
		},
		{
			"key": "myStartTime",
			"value": "",
			"type": "any",
			"enabled": true
		},
		{
			"key": "myEndTime",
			"value": "",
			"type": "any",
			"enabled": true
		}
	],
	"_postman_variable_scope": "environment",
	"_postman_exported_at": "2025-04-29T15:34:58.354Z",
	"_postman_exported_using": "Postman/11.39.4"
}